script_force_alignment.py
elevenlabs_srt_generator-1.2.2.dist-info/licenses/LICENSE
elevenlabs_srt_generator-1.2.2.dist-info/METADATA
elevenlabs_srt_generator-1.2.2.dist-info/WHEEL
elevenlabs_srt_generator-1.2.2.dist-info/entry_points.txt
elevenlabs_srt_generator-1.2.2.dist-info/top_level.txt
elevenlabs_srt_generator-1.2.2.dist-info/RECORD
