Metadata-Version: 2.4
Name: elevenlabs-srt-generator
Version: 1.2.2
Summary: Generate synchronized SRT subtitles using ElevenLabs Force Alignment API with AI-powered semantic segmentation
Home-page: https://github.com/preangelleo/script-force-alignment
Author: Script Force Alignment Contributors
Author-email: 
License: MIT
Project-URL: Homepage, https://github.com/preangelleo/script-force-alignment
Project-URL: Documentation, https://github.com/preangelleo/script-force-alignment#readme
Project-URL: Repository, https://github.com/preangelleo/script-force-alignment
Project-URL: Issues, https://github.com/preangelleo/script-force-alignment/issues
Keywords: subtitles,srt,elevenlabs,force-alignment,speech-to-text,transcription,ai,gemini,bilingual
Classifier: Development Status :: 5 - Production/Stable
Classifier: Intended Audience :: Developers
Classifier: Intended Audience :: End Users/Desktop
Classifier: Topic :: Multimedia :: Sound/Audio :: Speech
Classifier: Topic :: Multimedia :: Video
Classifier: Topic :: Text Processing :: Linguistic
Classifier: License :: OSI Approved :: MIT License
Classifier: Operating System :: OS Independent
Classifier: Programming Language :: Python :: 3
Classifier: Programming Language :: Python :: 3.7
Classifier: Programming Language :: Python :: 3.8
Classifier: Programming Language :: Python :: 3.9
Classifier: Programming Language :: Python :: 3.10
Classifier: Programming Language :: Python :: 3.11
Classifier: Programming Language :: Python :: 3.12
Requires-Python: >=3.7
License-File: LICENSE
Requires-Dist: requests>=2.31.0
Requires-Dist: python-dotenv>=1.0.0
Requires-Dist: google-generativeai>=0.8.0
Provides-Extra: dev
Requires-Dist: pytest>=7.4.0; extra == "dev"
Requires-Dist: pytest-cov>=4.1.0; extra == "dev"
Requires-Dist: black>=23.0.0; extra == "dev"
Requires-Dist: flake8>=6.0.0; extra == "dev"
Requires-Dist: build>=0.10.0; extra == "dev"
Requires-Dist: twine>=4.0.0; extra == "dev"
Dynamic: home-page
Dynamic: license-file
Dynamic: requires-python
